pylox/__init__.py
pylox/ast_printer.py
pylox/builtins/__init__.py
pylox/builtins/array_sum.lox
pylox/builtins/hello_world.lox
pylox/builtins/map.lox
pylox/builtins/py_builtins.py
pylox/builtins/split_on.lox
pylox/callable.py
pylox/containers/__init__.py
pylox/containers/array.py
pylox/containers/base.py
pylox/environment.py
pylox/error.py
pylox/grammar.py
pylox/interpreter.py
pylox/lox.py
pylox/parser.py
pylox/preprocessor.py
pylox/protocols/__init__.py
pylox/protocols/interpreter.py
pylox/protocols/typing.py
pylox/protocols/visitor.py
pylox/resolver.py
pylox/scanner.py
pylox/tokens.py
sco1_pylox-0.5.2.dist-info/licenses/LICENSE
sco1_pylox-0.5.2.dist-info/WHEEL
sco1_pylox-0.5.2.dist-info/entry_points.txt
sco1_pylox-0.5.2.dist-info/METADATA
sco1_pylox-0.5.2.dist-info/RECORD
