Metadata-Version: 2.4
Name: sco1-pylox
Version: 0.5.2
Summary: A Python interpreter for the Lox programming language.
Author: sco1
Author-email: sco1 <sco1.git@gmail.com>
License-Expression: MIT
License-File: LICENSE
Classifier: Development Status :: 5 - Production/Stable
Classifier: Environment :: Console
Classifier: Intended Audience :: Developers
Classifier: Operating System :: OS Independent
Classifier: Programming Language :: Python :: 3
Classifier: Programming Language :: Python :: 3.12
Classifier: Programming Language :: Python :: 3.13
Classifier: Programming Language :: Python :: 3.14
Classifier: Topic :: Software Development :: Interpreters
Classifier: Typing :: Typed
Requires-Dist: rich~=14.0
Requires-Dist: typer~=0.12
Requires-Python: >=3.12
Project-URL: Changelog, https://github.com/sco1/pylox/blob/main/CHANGELOG.md
Project-URL: Documentation, https://github.com/sco1/pylox/blob/main/README.md
Project-URL: Homepage, https://github.com/sco1/
Project-URL: Issues, https://github.com/sco1/pylox/issues
Project-URL: Repository, https://github.com/sco1/pylox
